ARPkeras/__init__.py
ARPkeras/autorotating_conv.py
ARPkeras/autorotating_dense.py
arpkeras-1.0.0.dist-info/LICENSE
arpkeras-1.0.0.dist-info/METADATA
arpkeras-1.0.0.dist-info/WHEEL
arpkeras-1.0.0.dist-info/top_level.txt
arpkeras-1.0.0.dist-info/RECORD
