Metadata-Version: 2.1
Name: arpkeras
Version: 1.0.0
Summary: Auto-Rotating Perceptron implementation for Keras.
Home-page: https://github.com/DanielSaromo/ARP
Author: Daniel Saromo
Author-email: danielsaromo@gmail.com
License: UNKNOWN
Platform: UNKNOWN
Classifier: Programming Language :: Python :: 3
Classifier: License :: OSI Approved :: Apache Software License
Classifier: Operating System :: OS Independent
Requires-Python: >=3
